isehole/Active Directory/CSV/.gitignore
isehole/Active Directory/HTML/.gitignore
isehole/Active Directory/JSON/.gitignore
isehole/Active Directory/Markdown/.gitignore
isehole/Active Directory/Mindmap/.gitignore
isehole/Active Directory/YAML/.gitignore
isehole/Active Sessions/HTML/.gitignore
isehole/Active Sessions/JSON/.gitignore
isehole/Active Sessions/Markdown/.gitignore
isehole/Active Sessions/Mindmap/.gitignore
isehole/Active Sessions/YAML/.gitignore
isehole/Admin Users/CSV/.gitignore
isehole/Admin Users/HTML/.gitignore
isehole/Admin Users/JSON/.gitignore
isehole/Admin Users/Markdown/.gitignore
isehole/Admin Users/Mindmap/.gitignore
isehole/Admin Users/YAML/.gitignore
isehole/Allowed Protocols/CSV/.gitignore
isehole/Allowed Protocols/HTML/.gitignore
isehole/Allowed Protocols/JSON/.gitignore
isehole/Allowed Protocols/Markdown/.gitignore
isehole/Allowed Protocols/Mindmap/.gitignore
isehole/Allowed Protocols/YAML/.gitignore
isehole/Authentication Dictionaries/CSV/.gitignore
isehole/Authentication Dictionaries/HTML/.gitignore
isehole/Authentication Dictionaries/JSON/.gitignore
isehole/Authentication Dictionaries/Markdown/.gitignore
isehole/Authentication Dictionaries/Mindmap/.gitignore
isehole/Authentication Dictionaries/YAML/.gitignore
isehole/Authorization Dictionaries/CSV/.gitignore
isehole/Authorization Dictionaries/HTML/.gitignore
isehole/Authorization Dictionaries/JSON/.gitignore
isehole/Authorization Dictionaries/Markdown/.gitignore
isehole/Authorization Dictionaries/Mindmap/.gitignore
isehole/Authorization Dictionaries/YAML/.gitignore
isehole/Authorization Profiles/CSV/.gitignore
isehole/Authorization Profiles/HTML/.gitignore
isehole/Authorization Profiles/JSON/.gitignore
isehole/Authorization Profiles/Markdown/.gitignore
isehole/Authorization Profiles/Mindmap/.gitignore
isehole/Authorization Profiles/YAML/.gitignore
isehole/CSRs/CSV/.gitignore
isehole/CSRs/HTML/.gitignore
isehole/CSRs/JSON/.gitignore
isehole/CSRs/Markdown/.gitignore
isehole-0.1.1.dist-info/METADATA
isehole-0.1.1.dist-info/WHEEL
isehole-0.1.1.dist-info/LICENSE
isehole-0.1.1.dist-info/entry_points.txt
isehole-0.1.1.dist-info/RECORD
